sfrs_element_loader/__init__.py
sfrs_element_loader/access_database.py
sfrs_element_loader/model.py
sfrs_element_loader-0.2.23.dist-info/LICENSE
sfrs_element_loader-0.2.23.dist-info/METADATA
sfrs_element_loader-0.2.23.dist-info/WHEEL
sfrs_element_loader-0.2.23.dist-info/top_level.txt
sfrs_element_loader-0.2.23.dist-info/RECORD
