Metadata-Version: 2.1
Name: sfrs-element-loader
Version: 0.2.23
Summary: A tool to load and inspect SFRS elements from a database using SQLAlchemy.
Author: Achim Andres
Author-email: a.andres@gsi.de
Classifier: Programming Language :: Python :: 3
Classifier: Operating System :: OS Independent
License-File: LICENSE
Requires-Dist: SQLAlchemy
Requires-Dist: tabulate
Requires-Dist: python-dotenv
